payelink_agent_search/__init__.py
payelink_agent_search/_version.py
payelink_agent_search/client.py
payelink_agent_search/config.py
payelink_agent_search/errors.py
payelink_agent_search/models.py
payelink_agent_search/transport.py
payelink_agent_search-0.1.4.dist-info/METADATA
payelink_agent_search-0.1.4.dist-info/WHEEL
payelink_agent_search-0.1.4.dist-info/licenses/LICENSE
payelink_agent_search-0.1.4.dist-info/RECORD
