Metadata-Version: 2.4
Name: payelink-agent-search
Version: 0.1.4
Summary: Python client for the Payelink Agent Search API.
License-File: LICENSE
Keywords: agents,payelink-agent-search,sdk
Classifier: Operating System :: OS Independent
Classifier: Programming Language :: Python :: 3
Requires-Python: >=3.13
Requires-Dist: httpx>=0.24.0
Requires-Dist: pydantic>=2.0.0
